setup.py
ASCII_Game.egg-info/PKG-INFO
ASCII_Game.egg-info/SOURCES.txt
ASCII_Game.egg-info/dependency_links.txt
ASCII_Game.egg-info/entry_points.txt
ASCII_Game.egg-info/not-zip-safe
ASCII_Game.egg-info/requires.txt
ASCII_Game.egg-info/top_level.txt
ascii_game/__init__.py
ascii_game/game.py
ascii_game/player.py
ascii_game.egg-info/PKG-INFO
ascii_game.egg-info/SOURCES.txt
ascii_game.egg-info/dependency_links.txt
ascii_game.egg-info/entry_points.txt
ascii_game.egg-info/not-zip-safe
ascii_game.egg-info/requires.txt
ascii_game.egg-info/top_level.txt
ascii_game/game_display/__init__.py
ascii_game/game_display/ascii_art.py
ascii_game/game_display/display.py
ascii_game/game_display/input_tools.py