Metadata-Version: 1.0
Name: ascii-game
Version: 0.0.3
Summary: Terminal-Based Game Framework
Home-page: https://github.com/lauryndbrown/AsciiGame
Author: Lauryn Brown
Author-email: lauryndbrown@gmail.com
License: GNU GPLv3
Platform: UNKNOWN
